envs/__init__.py
envs/baird.py
envs/base_mdp.py
envs/env_utils.py
envs/random_walk_dependent.py
envs/random_walk_tabular.py
test_mdp-0.0.1.dist-info/METADATA
test_mdp-0.0.1.dist-info/WHEEL
test_mdp-0.0.1.dist-info/top_level.txt
test_mdp-0.0.1.dist-info/RECORD
