Metadata-Version: 2.4
Name: test-mdp
Version: 0.0.1
Summary: test for policy evaluation examples
Home-page: https://github.com/limaries30/test-mdp
Author: teddylee777
Author-email: limaries30@kaist.ac.kr
Keywords: policy evaluation
Classifier: Programming Language :: Python :: 3.6
Classifier: Programming Language :: Python :: 3.7
Classifier: Programming Language :: Python :: 3.8
Classifier: Programming Language :: Python :: 3.9
Requires-Python: >=3.6
Requires-Dist: tqdm
Dynamic: author
Dynamic: author-email
Dynamic: classifier
Dynamic: home-page
Dynamic: keywords
Dynamic: requires-dist
Dynamic: requires-python
Dynamic: summary
